Metadata-Version: 2.1
Name: pdfer
Version: 0.1.3
Summary: The package will help you parse PDFs to data.
Home-page: https://github.com/lollococce/pdfer
Author: Lorenzo Coacci
Author-email: lorenzo@coacci.it
License: MIT License
